MANIFEST.in
README
new-theme.py
setup.py
Flask_Themes.egg-info/PKG-INFO
Flask_Themes.egg-info/SOURCES.txt
Flask_Themes.egg-info/dependency_links.txt
Flask_Themes.egg-info/namespace_packages.txt
Flask_Themes.egg-info/not-zip-safe
Flask_Themes.egg-info/requires.txt
Flask_Themes.egg-info/top_level.txt
base_theme/info.json
base_theme/license.txt
base_theme/static/style.css
base_theme/templates/layout.html
flaskext/__init__.py
flaskext/themes.py
tests/test-themes.py
tests/morethemes/cool/info.json
tests/morethemes/cool/templates/active.html
tests/morethemes/cool/templates/hello.html
tests/morethemes/cool/templates/static.html
tests/templates/active.html
tests/templates/hello.html
tests/templates/static.html
tests/templates/static_parent.html
tests/themes/cool/info.json
tests/themes/cool/templates/hello.html
tests/themes/identifier/info.json
tests/themes/notthis/info.json
tests/themes/plain/info.json
tests/themes/plain/license.txt
tests/themes/plain/templates/static.html
tests/themes/warm-theme/info.json