Metadata-Version: 1.0
Name: Flask-Themes
Version: 0.1.2
Summary: Provides infrastructure for theming Flask applications
Home-page: http://bitbucket.org/leafstorm/flask-themes/
Author: Matthew "LeafStorm" Frazier
Author-email: leafstormrush@gmail.com
License: MIT
Platform: any
Classifier: Development Status :: 4 - Beta
Classifier: Environment :: Web Environment
Classifier: Intended Audience :: Developers
Classifier: License :: OSI Approved :: MIT License
Classifier: Operating System :: OS Independent
Classifier: Programming Language :: Python
Classifier: Topic :: Internet :: WWW/HTTP :: Dynamic Content
Classifier: Topic :: Software Development :: Libraries :: Python Modules
